znvault/__init__.py
znvault/client.py
znvault/config.py
znvault/py.typed
znvault/admin/__init__.py
znvault/admin/policies.py
znvault/admin/roles.py
znvault/admin/tenants.py
znvault/admin/users.py
znvault/audit/__init__.py
znvault/audit/client.py
znvault/auth/__init__.py
znvault/auth/client.py
znvault/certificates/__init__.py
znvault/certificates/client.py
znvault/exceptions/__init__.py
znvault/exceptions/errors.py
znvault/health/__init__.py
znvault/health/client.py
znvault/http/__init__.py
znvault/http/client.py
znvault/kms/__init__.py
znvault/kms/client.py
znvault/models/__init__.py
znvault/models/admin.py
znvault/models/audit.py
znvault/models/auth.py
znvault/models/certificates.py
znvault/models/common.py
znvault/models/health.py
znvault/models/kms.py
znvault/models/secrets.py
znvault/secrets/__init__.py
znvault/secrets/client.py
znvault-1.8.0.dist-info/METADATA
znvault-1.8.0.dist-info/WHEEL
znvault-1.8.0.dist-info/top_level.txt
znvault-1.8.0.dist-info/RECORD
