Metadata-Version: 2.4
Name: znvault
Version: 1.8.0
Summary: Python SDK for ZnVault secrets management
Author-email: ZincApp Team <dev@zincapp.com>
License: Apache-2.0
Project-URL: Homepage, https://github.com/vidaldiego/zn-vault-sdk-python
Project-URL: Documentation, https://github.com/vidaldiego/zn-vault-sdk-python#readme
Project-URL: Repository, https://github.com/vidaldiego/zn-vault-sdk-python.git
Project-URL: Issues, https://github.com/vidaldiego/zn-vault-sdk-python/issues
Keywords: secrets,vault,security,kms,encryption
Classifier: Development Status :: 4 - Beta
Classifier: Intended Audience :: Developers
Classifier: License :: OSI Approved :: Apache Software License
Classifier: Operating System :: OS Independent
Classifier: Programming Language :: Python :: 3
Classifier: Programming Language :: Python :: 3.9
Classifier: Programming Language :: Python :: 3.10
Classifier: Programming Language :: Python :: 3.11
Classifier: Programming Language :: Python :: 3.12
Classifier: Topic :: Security
Classifier: Topic :: Security :: Cryptography
Classifier: Typing :: Typed
Requires-Python: >=3.9
Requires-Dist: requests>=2.28.0
Requires-Dist: urllib3>=1.26.0
Provides-Extra: dev
Requires-Dist: pytest>=7.0.0; extra == "dev"
Requires-Dist: pytest-cov>=4.0.0; extra == "dev"
Requires-Dist: pytest-asyncio>=0.21.0; extra == "dev"
Requires-Dist: mypy>=1.0.0; extra == "dev"
Requires-Dist: ruff>=0.1.0; extra == "dev"
Requires-Dist: types-requests>=2.28.0; extra == "dev"
Provides-Extra: async
Requires-Dist: aiohttp>=3.8.0; extra == "async"
